analysis/__init__.py
analysis/analysis_functions.py
data_handling/__init__.py
data_handling/data_operations.py
gui/__init__.py
gui/main_gui.py
gui/widgets/__init__.py
gui/widgets/custom_button.py
gui/widgets/draggable_widget.py
gui/wizards/__init__.py
gui/wizards/feature_engineering_wizard.py
gui/wizards/import_wizard.py
machine_learning/__init__.py
machine_learning/ml_models.py
visualization/__init__.py
visualization/visualization_functions.py
DataSpark-0.1.0.dist-info/LICENSE.md
DataSpark-0.1.0.dist-info/METADATA
DataSpark-0.1.0.dist-info/WHEEL
DataSpark-0.1.0.dist-info/entry_points.txt
DataSpark-0.1.0.dist-info/top_level.txt
DataSpark-0.1.0.dist-info/RECORD
